{
    "0": {
        "0.05131670194948623": {
            "0": 97.52,
            "1": 98.0,
            "hypercube": 96.32
        },
        "0.10557280900008414": {
            "0": 92.47999999999999,
            "1": 85.52,
            "hypercube": 81.67999999999999
        },
        "0.16333997346592444": {
            "0": 87.44,
            "1": 79.44,
            "hypercube": 72.08
        },
        "0.2254033307585166": {
            "0": 83.84,
            "1": 75.2,
            "hypercube": 66.08000000000001
        },
        "0.2928932188134524": {
            "0": 78.32000000000001,
            "1": 68.0,
            "hypercube": 55.67999999999999
        },
        "0.3675444679663241": {
            "0": 67.84,
            "1": 63.519999999999996,
            "hypercube": 45.36
        },
        "0.4522774424948338": {
            "0": 59.36,
            "1": 59.28,
            "hypercube": 36.96
        },
        "0.5527864045000421": {
            "0": 49.120000000000005,
            "1": 49.84,
            "hypercube": 25.919999999999998
        },
        "0.6837722339831621": {
            "0": 30.880000000000003,
            "1": 38.48,
            "hypercube": 13.68
        }
    },
    "1": {
        "0.05131670194948623": {
            "0": 96.48,
            "1": 96.64,
            "hypercube": 94.88
        },
        "0.10557280900008414": {
            "0": 92.47999999999999,
            "1": 89.92,
            "hypercube": 86.08
        },
        "0.16333997346592444": {
            "0": 88.64,
            "1": 86.56,
            "hypercube": 79.84
        },
        "0.2254033307585166": {
            "0": 84.72,
            "1": 81.76,
            "hypercube": 72.39999999999999
        },
        "0.2928932188134524": {
            "0": 76.08,
            "1": 76.08,
            "hypercube": 60.0
        },
        "0.3675444679663241": {
            "0": 71.76,
            "1": 66.08000000000001,
            "hypercube": 49.2
        },
        "0.4522774424948338": {
            "0": 56.24,
            "1": 55.92,
            "hypercube": 33.92
        },
        "0.5527864045000421": {
            "0": 43.519999999999996,
            "1": 46.64,
            "hypercube": 23.200000000000003
        },
        "0.6837722339831621": {
            "0": 33.52,
            "1": 31.6,
            "hypercube": 13.919999999999998
        }
    },
    "2": {
        "0.05131670194948623": {
            "0": 95.92,
            "1": 93.67999999999999,
            "hypercube": 92.56
        },
        "0.10557280900008414": {
            "0": 88.48,
            "1": 84.0,
            "hypercube": 77.60000000000001
        },
        "0.16333997346592444": {
            "0": 84.8,
            "1": 79.44,
            "hypercube": 70.72
        },
        "0.2254033307585166": {
            "0": 79.67999999999999,
            "1": 74.0,
            "hypercube": 62.08
        },
        "0.2928932188134524": {
            "0": 70.39999999999999,
            "1": 66.47999999999999,
            "hypercube": 49.519999999999996
        },
        "0.3675444679663241": {
            "0": 56.56,
            "1": 54.400000000000006,
            "hypercube": 32.48
        },
        "0.4522774424948338": {
            "0": 49.6,
            "1": 51.92,
            "hypercube": 27.76
        },
        "0.5527864045000421": {
            "0": 40.239999999999995,
            "1": 45.04,
            "hypercube": 20.48
        },
        "0.6837722339831621": {
            "0": 30.240000000000002,
            "1": 33.92,
            "hypercube": 11.68
        }
    },
    "3": {
        "0.05131670194948623": {
            "0": 97.11999999999999,
            "1": 96.08,
            "hypercube": 94.8
        },
        "0.10557280900008414": {
            "0": 94.08,
            "1": 91.12,
            "hypercube": 87.36
        },
        "0.16333997346592444": {
            "0": 90.64,
            "1": 87.68,
            "hypercube": 81.36
        },
        "0.2254033307585166": {
            "0": 84.64,
            "1": 80.47999999999999,
            "hypercube": 70.0
        },
        "0.2928932188134524": {
            "0": 77.12,
            "1": 70.08,
            "hypercube": 55.76
        },
        "0.3675444679663241": {
            "0": 69.84,
            "1": 65.12,
            "hypercube": 47.52
        },
        "0.4522774424948338": {
            "0": 58.96,
            "1": 56.08,
            "hypercube": 34.96
        },
        "0.5527864045000421": {
            "0": 45.28,
            "1": 47.199999999999996,
            "hypercube": 23.84
        },
        "0.6837722339831621": {
            "0": 28.48,
            "1": 28.48,
            "hypercube": 9.120000000000001
        }
    },
    "4": {
        "0.05131670194948623": {
            "0": 95.52000000000001,
            "1": 97.76,
            "hypercube": 95.28
        },
        "0.10557280900008414": {
            "0": 92.32000000000001,
            "1": 91.84,
            "hypercube": 88.32
        },
        "0.16333997346592444": {
            "0": 89.44,
            "1": 87.03999999999999,
            "hypercube": 81.2
        },
        "0.2254033307585166": {
            "0": 86.56,
            "1": 81.92,
            "hypercube": 73.6
        },
        "0.2928932188134524": {
            "0": 81.52000000000001,
            "1": 75.92,
            "hypercube": 64.16
        },
        "0.3675444679663241": {
            "0": 68.24,
            "1": 65.12,
            "hypercube": 46.239999999999995
        },
        "0.4522774424948338": {
            "0": 59.599999999999994,
            "1": 55.2,
            "hypercube": 34.4
        },
        "0.5527864045000421": {
            "0": 50.080000000000005,
            "1": 44.64,
            "hypercube": 23.04
        },
        "0.6837722339831621": {
            "0": 36.08,
            "1": 30.240000000000002,
            "hypercube": 11.600000000000001
        }
    },
    "5": {
        "0.05131670194948623": {
            "0": 95.43634907926342,
            "1": 96.07686148919136,
            "hypercube": 94.07526020816654
        },
        "0.10557280900008414": {
            "0": 87.34987990392314,
            "1": 87.26981585268214,
            "hypercube": 80.38430744595676
        },
        "0.16333997346592444": {
            "0": 83.10648518815053,
            "1": 82.14571657325861,
            "hypercube": 71.57726180944756
        },
        "0.2254033307585166": {
            "0": 77.74219375500401,
            "1": 77.18174539631705,
            "hypercube": 62.93034427542034
        },
        "0.2928932188134524": {
            "0": 72.1377101681345,
            "1": 68.29463570856686,
            "hypercube": 52.041633306645316
        },
        "0.3675444679663241": {
            "0": 68.77502001601282,
            "1": 63.49079263410729,
            "hypercube": 46.27702161729383
        },
        "0.4522774424948338": {
            "0": 57.245796637309844,
            "1": 57.405924739791836,
            "hypercube": 35.22818254603683
        },
        "0.5527864045000421": {
            "0": 47.87830264211369,
            "1": 47.71817453963171,
            "hypercube": 24.419535628502803
        },
        "0.6837722339831621": {
            "0": 35.14811849479584,
            "1": 34.58767013610889,
            "hypercube": 13.530824659727783
        }
    },
    "6": {
        "0.05131670194948623": {
            "0": 96.87750200160127,
            "1": 94.95596477181746,
            "hypercube": 93.91513210568455
        },
        "0.10557280900008414": {
            "0": 90.23218574859888,
            "1": 89.51160928742993,
            "hypercube": 83.90712570056044
        },
        "0.16333997346592444": {
            "0": 82.94635708566854,
            "1": 85.58847077662129,
            "hypercube": 73.97918334667735
        },
        "0.2254033307585166": {
            "0": 75.5004003202562,
            "1": 77.90232185748599,
            "hypercube": 61.569255404323464
        },
        "0.2928932188134524": {
            "0": 67.09367493995197,
            "1": 72.61809447558046,
            "hypercube": 51.00080064051241
        },
        "0.3675444679663241": {
            "0": 61.569255404323464,
            "1": 62.53002401921537,
            "hypercube": 40.43234587670136
        },
        "0.4522774424948338": {
            "0": 52.28182546036829,
            "1": 54.12329863891113,
            "hypercube": 30.184147317854283
        },
        "0.5527864045000421": {
            "0": 40.51240992794236,
            "1": 47.55804643714972,
            "hypercube": 22.257806244995997
        },
        "0.6837722339831621": {
            "0": 32.66613290632506,
            "1": 37.710168134507605,
            "hypercube": 15.532425940752603
        }
    },
    "7": {
        "0.05131670194948623": {
            "0": 97.27782225780625,
            "1": 96.7173738991193,
            "hypercube": 95.75660528422738
        },
        "0.10557280900008414": {
            "0": 93.1945556445156,
            "1": 90.23218574859888,
            "hypercube": 87.51000800640513
        },
        "0.16333997346592444": {
            "0": 90.0720576461169,
            "1": 87.10968775020017,
            "hypercube": 82.54603682946357
        },
        "0.2254033307585166": {
            "0": 84.78783026421138,
            "1": 84.14731785428343,
            "hypercube": 75.10008006405124
        },
        "0.2928932188134524": {
            "0": 78.38270616493195,
            "1": 72.85828662930345,
            "hypercube": 60.0480384307446
        },
        "0.3675444679663241": {
            "0": 73.09847878302642,
            "1": 63.3306645316253,
            "hypercube": 48.51881505204163
        },
        "0.4522774424948338": {
            "0": 63.971176941553246,
            "1": 55.964771817453965,
            "hypercube": 37.30984787830264
        },
        "0.5527864045000421": {
            "0": 57.806244995996806,
            "1": 44.35548438751001,
            "hypercube": 26.58126501200961
        },
        "0.6837722339831621": {
            "0": 36.269015212169734,
            "1": 31.46517213771017,
            "hypercube": 12.089671737389912
        }
    },
    "8": {
        "0.05131670194948623": {
            "0": 98.15852682145717,
            "1": 98.8791032826261,
            "hypercube": 97.59807846277022
        },
        "0.10557280900008414": {
            "0": 94.63570856685348,
            "1": 91.1929543634908,
            "hypercube": 88.71096877502002
        },
        "0.16333997346592444": {
            "0": 90.95276220976781,
            "1": 85.82866293034428,
            "hypercube": 80.86469175340272
        },
        "0.2254033307585166": {
            "0": 86.14891913530825,
            "1": 79.02321857485988,
            "hypercube": 70.13610888710969
        },
        "0.2928932188134524": {
            "0": 78.78302642113691,
            "1": 75.90072057646117,
            "hypercube": 62.04963971176941
        },
        "0.3675444679663241": {
            "0": 69.41553242594075,
            "1": 69.49559647718175,
            "hypercube": 49.71977582065652
        },
        "0.4522774424948338": {
            "0": 57.405924739791836,
            "1": 58.8470776621297,
            "hypercube": 34.34747798238591
        },
        "0.5527864045000421": {
            "0": 43.63490792634107,
            "1": 49.31945556445156,
            "hypercube": 22.257806244995997
        },
        "0.6837722339831621": {
            "0": 32.2658126501201,
            "1": 35.468374699759806,
            "hypercube": 12.650120096076861
        }
    },
    "9": {
        "0.05131670194948623": {
            "0": 93.67493995196156,
            "1": 89.43154523618895,
            "hypercube": 86.78943154523618
        },
        "0.10557280900008414": {
            "0": 89.03122497998399,
            "1": 84.62770216172937,
            "hypercube": 79.02321857485988
        },
        "0.16333997346592444": {
            "0": 82.38590872698158,
            "1": 80.0640512409928,
            "hypercube": 69.33546837469976
        },
        "0.2254033307585166": {
            "0": 81.1048839071257,
            "1": 72.93835068054445,
            "hypercube": 62.289831865492395
        },
        "0.2928932188134524": {
            "0": 71.65732586068854,
            "1": 66.53322658126501,
            "hypercube": 49.9599679743795
        },
        "0.3675444679663241": {
            "0": 65.49239391513211,
            "1": 61.72938350680545,
            "hypercube": 41.95356285028022
        },
        "0.4522774424948338": {
            "0": 51.32105684547638,
            "1": 50.600480384307446,
            "hypercube": 27.622097678142516
        },
        "0.5527864045000421": {
            "0": 42.514011208967176,
            "1": 39.47157726180945,
            "hypercube": 17.69415532425941
        },
        "0.6837722339831621": {
            "0": 27.942353883106485,
            "1": 25.22017614091273,
            "hypercube": 8.726981585268215
        }
    },
    "AVG": {
        "0.05131670194948623": {
            "0": 96.39851401120896,
            "1": 95.82208486789432,
            "hypercube": 94.19745076060849
        },
        "0.10557280900008414": {
            "0": 91.42835548438751,
            "1": 88.52342674139312,
            "hypercube": 84.05756285028022
        },
        "0.16333997346592444": {
            "0": 87.04235708566854,
            "1": 84.08965892714173,
            "hypercube": 76.35026421136908
        },
        "0.2254033307585166": {
            "0": 82.47242273819055,
            "1": 78.45529543634909,
            "hypercube": 67.6185620496397
        },
        "0.2928932188134524": {
            "0": 75.14944435548438,
            "1": 71.2764963971177,
            "hypercube": 56.02200800640512
        },
        "0.3675444679663241": {
            "0": 67.25906805444356,
            "1": 63.48164611689352,
            "hypercube": 44.77015212169736
        },
        "0.4522774424948338": {
            "0": 56.59857806244996,
            "1": 55.5341553242594,
            "hypercube": 33.26917534027221
        },
        "0.5527864045000421": {
            "0": 46.05858767013611,
            "1": 46.17827381905524,
            "hypercube": 22.96905684547638
        },
        "0.6837722339831621": {
            "0": 32.34914331465172,
            "1": 32.717156124899915,
            "hypercube": 12.253002401921538
        }
    },
    "STD": {
        "0.05131670194948623": {
            "0": 1.2340806270435634,
            "1": 2.561715017547486,
            "hypercube": 2.795638152898754
        },
        "0.10557280900008414": {
            "0": 2.365344743790983,
            "1": 2.7738994120979275,
            "hypercube": 3.9108983599858176
        },
        "0.16333997346592444": {
            "0": 3.2380803384677805,
            "1": 3.245179160736681,
            "hypercube": 4.971008636924726
        },
        "0.2254033307585166": {
            "0": 3.5757270306101434,
            "1": 3.5008188921885877,
            "hypercube": 4.966224464708663
        },
        "0.2928932188134524": {
            "0": 4.333132852634375,
            "1": 3.6997929569719212,
            "hypercube": 5.048351812631776
        },
        "0.3675444679663241": {
            "0": 4.682217816668824,
            "1": 3.671023071470014,
            "hypercube": 4.983102150312013
        },
        "0.4522774424948338": {
            "0": 4.162108473490412,
            "1": 2.620076794157092,
            "hypercube": 3.335697665833467
        },
        "0.5527864045000421": {
            "0": 5.0691985533907395,
            "1": 2.8420368962412033,
            "hypercube": 2.443535482896309
        },
        "0.6837722339831621": {
            "0": 2.821244615788327,
            "1": 3.921293195405127,
            "hypercube": 2.0097338558857687
        }
    }
}