{
    "0": {
        "0.025996253574703254": {
            "0": 97.68,
            "1": 97.52,
            "2": 97.76,
            "3": 96.96000000000001,
            "hypercube": 95.6
        },
        "0.05425839099682417": {
            "0": 94.8,
            "1": 94.56,
            "2": 94.64,
            "3": 94.48,
            "hypercube": 90.8
        },
        "0.08530878077130555": {
            "0": 91.52,
            "1": 89.68,
            "2": 92.08,
            "3": 91.28,
            "hypercube": 82.88
        },
        "0.11988826320660662": {
            "0": 89.36,
            "1": 86.56,
            "2": 89.2,
            "3": 87.83999999999999,
            "hypercube": 76.72
        },
        "0.1591035847462855": {
            "0": 86.16,
            "1": 81.12,
            "2": 85.36,
            "3": 82.96,
            "hypercube": 66.16
        },
        "0.20472927123294937": {
            "0": 81.92,
            "1": 76.16000000000001,
            "2": 81.12,
            "3": 76.08,
            "hypercube": 57.599999999999994
        },
        "0.25991719550771475": {
            "0": 74.8,
            "1": 69.6,
            "2": 76.48,
            "3": 70.08,
            "hypercube": 49.2
        },
        "0.331259695023578": {
            "0": 69.52000000000001,
            "1": 62.8,
            "2": 70.16,
            "3": 62.72,
            "hypercube": 39.36
        },
        "0.4376586748096509": {
            "0": 60.0,
            "1": 53.839999999999996,
            "2": 58.160000000000004,
            "3": 52.64,
            "hypercube": 26.32
        }
    },
    "1": {
        "0.025996253574703254": {
            "0": 96.24000000000001,
            "1": 96.72,
            "2": 96.56,
            "3": 96.39999999999999,
            "hypercube": 94.32000000000001
        },
        "0.05425839099682417": {
            "0": 93.92,
            "1": 94.48,
            "2": 94.0,
            "3": 93.60000000000001,
            "hypercube": 88.72
        },
        "0.08530878077130555": {
            "0": 90.64,
            "1": 90.24,
            "2": 90.88000000000001,
            "3": 90.96,
            "hypercube": 79.75999999999999
        },
        "0.11988826320660662": {
            "0": 87.92,
            "1": 85.2,
            "2": 86.8,
            "3": 86.08,
            "hypercube": 69.28
        },
        "0.1591035847462855": {
            "0": 84.64,
            "1": 80.64,
            "2": 83.91999999999999,
            "3": 81.04,
            "hypercube": 64.16
        },
        "0.20472927123294937": {
            "0": 80.24,
            "1": 76.72,
            "2": 78.56,
            "3": 76.16000000000001,
            "hypercube": 56.24
        },
        "0.25991719550771475": {
            "0": 74.24,
            "1": 71.52,
            "2": 75.03999999999999,
            "3": 71.84,
            "hypercube": 49.04
        },
        "0.331259695023578": {
            "0": 67.04,
            "1": 65.60000000000001,
            "2": 67.12,
            "3": 64.08,
            "hypercube": 37.28
        },
        "0.4376586748096509": {
            "0": 58.160000000000004,
            "1": 56.879999999999995,
            "2": 56.32,
            "3": 54.400000000000006,
            "hypercube": 23.200000000000003
        }
    },
    "2": {
        "0.025996253574703254": {
            "0": 97.2,
            "1": 94.88,
            "2": 97.04,
            "3": 96.08,
            "hypercube": 92.96
        },
        "0.05425839099682417": {
            "0": 93.12,
            "1": 92.56,
            "2": 94.72,
            "3": 92.4,
            "hypercube": 86.8
        },
        "0.08530878077130555": {
            "0": 90.96,
            "1": 89.84,
            "2": 90.24,
            "3": 89.2,
            "hypercube": 80.08
        },
        "0.11988826320660662": {
            "0": 85.68,
            "1": 85.04,
            "2": 85.6,
            "3": 84.56,
            "hypercube": 71.12
        },
        "0.1591035847462855": {
            "0": 82.32000000000001,
            "1": 79.67999999999999,
            "2": 81.67999999999999,
            "3": 80.47999999999999,
            "hypercube": 62.239999999999995
        },
        "0.20472927123294937": {
            "0": 77.84,
            "1": 74.88,
            "2": 78.16,
            "3": 74.96000000000001,
            "hypercube": 52.88
        },
        "0.25991719550771475": {
            "0": 70.96000000000001,
            "1": 69.44,
            "2": 71.52,
            "3": 68.0,
            "hypercube": 43.04
        },
        "0.331259695023578": {
            "0": 64.16,
            "1": 62.480000000000004,
            "2": 63.75999999999999,
            "3": 62.239999999999995,
            "hypercube": 33.6
        },
        "0.4376586748096509": {
            "0": 55.92,
            "1": 52.64,
            "2": 54.08,
            "3": 53.52,
            "hypercube": 21.12
        }
    },
    "3": {
        "0.025996253574703254": {
            "0": 97.28,
            "1": 97.84,
            "2": 97.6,
            "3": 97.44,
            "hypercube": 95.6
        },
        "0.05425839099682417": {
            "0": 95.28,
            "1": 95.12,
            "2": 95.28,
            "3": 94.16,
            "hypercube": 89.92
        },
        "0.08530878077130555": {
            "0": 91.84,
            "1": 92.16,
            "2": 91.84,
            "3": 90.64,
            "hypercube": 81.92
        },
        "0.11988826320660662": {
            "0": 89.2,
            "1": 89.44,
            "2": 89.03999999999999,
            "3": 87.83999999999999,
            "hypercube": 77.92
        },
        "0.1591035847462855": {
            "0": 85.6,
            "1": 84.08,
            "2": 84.88,
            "3": 84.32,
            "hypercube": 68.16
        },
        "0.20472927123294937": {
            "0": 80.72,
            "1": 79.92,
            "2": 80.47999999999999,
            "3": 80.0,
            "hypercube": 58.96
        },
        "0.25991719550771475": {
            "0": 75.36,
            "1": 73.28,
            "2": 75.6,
            "3": 74.16,
            "hypercube": 51.6
        },
        "0.331259695023578": {
            "0": 70.48,
            "1": 66.16,
            "2": 71.6,
            "3": 66.4,
            "hypercube": 42.32
        },
        "0.4376586748096509": {
            "0": 58.8,
            "1": 54.879999999999995,
            "2": 60.96,
            "3": 55.120000000000005,
            "hypercube": 26.72
        }
    },
    "4": {
        "0.025996253574703254": {
            "0": 97.68,
            "1": 95.76,
            "2": 97.52,
            "3": 96.88,
            "hypercube": 94.96
        },
        "0.05425839099682417": {
            "0": 94.88,
            "1": 93.2,
            "2": 95.04,
            "3": 93.52000000000001,
            "hypercube": 88.64
        },
        "0.08530878077130555": {
            "0": 91.12,
            "1": 90.56,
            "2": 91.44,
            "3": 91.03999999999999,
            "hypercube": 81.04
        },
        "0.11988826320660662": {
            "0": 87.28,
            "1": 86.08,
            "2": 87.6,
            "3": 86.72,
            "hypercube": 72.48
        },
        "0.1591035847462855": {
            "0": 84.48,
            "1": 83.6,
            "2": 84.48,
            "3": 83.91999999999999,
            "hypercube": 66.88
        },
        "0.20472927123294937": {
            "0": 81.44,
            "1": 79.52,
            "2": 80.80000000000001,
            "3": 79.84,
            "hypercube": 56.08
        },
        "0.25991719550771475": {
            "0": 75.12,
            "1": 74.96000000000001,
            "2": 76.96,
            "3": 72.48,
            "hypercube": 44.96
        },
        "0.331259695023578": {
            "0": 67.84,
            "1": 67.04,
            "2": 71.44,
            "3": 65.84,
            "hypercube": 32.56
        },
        "0.4376586748096509": {
            "0": 59.199999999999996,
            "1": 56.08,
            "2": 59.519999999999996,
            "3": 57.76,
            "hypercube": 18.88
        }
    },
    "5": {
        "0.025996253574703254": {
            "0": 98.15852682145717,
            "1": 96.55724579663732,
            "2": 98.15852682145717,
            "3": 97.19775820656525,
            "hypercube": 95.5964771817454
        },
        "0.05425839099682417": {
            "0": 93.75500400320256,
            "1": 94.79583666933547,
            "2": 94.4755804643715,
            "3": 94.79583666933547,
            "hypercube": 90.63250600480384
        },
        "0.08530878077130555": {
            "0": 91.43314651721377,
            "1": 91.99359487590073,
            "2": 90.87269815852682,
            "3": 92.55404323458767,
            "hypercube": 84.30744595676542
        },
        "0.11988826320660662": {
            "0": 88.871096877502,
            "1": 87.9103282626101,
            "2": 87.6701361088871,
            "3": 90.23218574859888,
            "hypercube": 77.10168134507606
        },
        "0.1591035847462855": {
            "0": 84.94795836669336,
            "1": 85.18815052041633,
            "2": 83.66693354683747,
            "3": 85.74859887910328,
            "hypercube": 68.77502001601282
        },
        "0.20472927123294937": {
            "0": 78.06244995996798,
            "1": 80.94475580464372,
            "2": 79.26341072858285,
            "3": 80.62449959967975,
            "hypercube": 56.204963971176944
        },
        "0.25991719550771475": {
            "0": 73.01841473178543,
            "1": 74.13931144915932,
            "2": 73.81905524419535,
            "3": 75.6605284227382,
            "hypercube": 46.35708566853482
        },
        "0.331259695023578": {
            "0": 65.41232986389112,
            "1": 69.09527622097679,
            "2": 66.53322658126501,
            "3": 69.41553242594075,
            "hypercube": 36.74939951961569
        },
        "0.4376586748096509": {
            "0": 57.64611689351481,
            "1": 59.72778222578062,
            "2": 57.16573258606885,
            "3": 60.20816653322658,
            "hypercube": 22.898318654923937
        }
    },
    "6": {
        "0.025996253574703254": {
            "0": 96.79743795036029,
            "1": 97.27782225780625,
            "2": 96.47718174539631,
            "3": 96.87750200160127,
            "hypercube": 94.4755804643715
        },
        "0.05425839099682417": {
            "0": 94.07526020816654,
            "1": 94.71577261809448,
            "2": 93.43474779823859,
            "3": 94.31545236188951,
            "hypercube": 88.71096877502002
        },
        "0.08530878077130555": {
            "0": 90.63250600480384,
            "1": 91.75340272217774,
            "2": 90.71257005604484,
            "3": 92.2337870296237,
            "hypercube": 82.2257806244996
        },
        "0.11988826320660662": {
            "0": 88.871096877502,
            "1": 89.27141713370696,
            "2": 88.47077662129705,
            "3": 88.39071257005604,
            "hypercube": 77.18174539631705
        },
        "0.1591035847462855": {
            "0": 86.14891913530825,
            "1": 84.86789431545236,
            "2": 84.70776621297038,
            "3": 84.30744595676542,
            "hypercube": 68.61489191353083
        },
        "0.20472927123294937": {
            "0": 81.50520416333067,
            "1": 79.82385908726981,
            "2": 81.50520416333067,
            "3": 79.74379503602881,
            "hypercube": 58.8470776621297
        },
        "0.25991719550771475": {
            "0": 75.74059247397919,
            "1": 74.05924739791834,
            "2": 76.22097678142514,
            "3": 75.18014411529224,
            "hypercube": 51.881505204163325
        },
        "0.331259695023578": {
            "0": 68.61489191353083,
            "1": 66.37309847878302,
            "2": 68.69495596477182,
            "3": 68.05444355484389,
            "hypercube": 38.59087269815853
        },
        "0.4376586748096509": {
            "0": 57.405924739791836,
            "1": 57.245796637309844,
            "2": 57.56605284227382,
            "3": 56.12489991993594,
            "hypercube": 24.339471577261808
        }
    },
    "7": {
        "0.025996253574703254": {
            "0": 97.27782225780625,
            "1": 97.67814251401121,
            "2": 97.51801441152922,
            "3": 97.27782225780625,
            "hypercube": 95.43634907926342
        },
        "0.05425839099682417": {
            "0": 94.55564451561249,
            "1": 94.63570856685348,
            "2": 94.23538831064852,
            "3": 94.4755804643715,
            "hypercube": 90.23218574859888
        },
        "0.08530878077130555": {
            "0": 91.35308246597278,
            "1": 90.95276220976781,
            "2": 92.07365892714171,
            "3": 90.47237790232185,
            "hypercube": 81.74539631705365
        },
        "0.11988826320660662": {
            "0": 89.11128903122498,
            "1": 86.46917534027222,
            "2": 86.86949559647718,
            "3": 86.30904723779024,
            "hypercube": 74.85988791032825
        },
        "0.1591035847462855": {
            "0": 85.66853482786229,
            "1": 83.18654923939151,
            "2": 82.38590872698158,
            "3": 82.14571657325861,
            "hypercube": 65.33226581265012
        },
        "0.20472927123294937": {
            "0": 80.46437149719776,
            "1": 78.54283426741392,
            "2": 78.78302642113691,
            "3": 78.70296236989591,
            "hypercube": 55.88470776621297
        },
        "0.25991719550771475": {
            "0": 75.6605284227382,
            "1": 73.65892714171338,
            "2": 73.2586068855084,
            "3": 72.93835068054445,
            "hypercube": 48.83907125700561
        },
        "0.331259695023578": {
            "0": 67.41393114491594,
            "1": 67.49399519615693,
            "2": 67.41393114491594,
            "3": 65.73258606885508,
            "hypercube": 39.71176941553243
        },
        "0.4376586748096509": {
            "0": 55.564451561248994,
            "1": 55.484387510008006,
            "2": 55.64451561248999,
            "3": 54.12329863891113,
            "hypercube": 22.177742193755005
        }
    },
    "8": {
        "0.025996253574703254": {
            "0": 98.31865492393915,
            "1": 97.19775820656525,
            "2": 98.23859087269817,
            "3": 97.35788630904723,
            "hypercube": 95.99679743795036
        },
        "0.05425839099682417": {
            "0": 96.47718174539631,
            "1": 94.79583666933547,
            "2": 96.55724579663732,
            "3": 94.55564451561249,
            "hypercube": 92.1537229783827
        },
        "0.08530878077130555": {
            "0": 93.03442754203363,
            "1": 90.87269815852682,
            "2": 93.2746196957566,
            "3": 91.67333867093676,
            "hypercube": 82.94635708566854
        },
        "0.11988826320660662": {
            "0": 91.03282626100881,
            "1": 86.86949559647718,
            "2": 89.51160928742993,
            "3": 87.8302642113691,
            "hypercube": 76.5412329863891
        },
        "0.1591035847462855": {
            "0": 85.42834267413932,
            "1": 83.98718975180144,
            "2": 86.06885508406725,
            "3": 83.66693354683747,
            "hypercube": 67.41393114491594
        },
        "0.20472927123294937": {
            "0": 82.62610088070457,
            "1": 79.90392313851082,
            "2": 81.82546036829463,
            "3": 78.46277021617294,
            "hypercube": 60.368294635708565
        },
        "0.25991719550771475": {
            "0": 78.38270616493195,
            "1": 74.13931144915932,
            "2": 78.06244995996798,
            "3": 73.89911929543635,
            "hypercube": 53.08246597277822
        },
        "0.331259695023578": {
            "0": 70.21617293835068,
            "1": 66.61329063250601,
            "2": 70.45636509207365,
            "3": 66.693354683747,
            "hypercube": 38.75100080064051
        },
        "0.4376586748096509": {
            "0": 58.28662930344275,
            "1": 57.00560448358687,
            "2": 59.167333867093674,
            "3": 53.64291433146518,
            "hypercube": 22.978382706164933
        }
    },
    "9": {
        "0.025996253574703254": {
            "0": 96.47718174539631,
            "1": 94.79583666933547,
            "2": 96.79743795036029,
            "3": 95.27622097678142,
            "hypercube": 93.03442754203363
        },
        "0.05425839099682417": {
            "0": 93.67493995196156,
            "1": 91.67333867093676,
            "2": 93.51481184947959,
            "3": 90.15212169735788,
            "hypercube": 83.98718975180144
        },
        "0.08530878077130555": {
            "0": 90.63250600480384,
            "1": 88.55084067253803,
            "2": 90.79263410728583,
            "3": 88.15052041633307,
            "hypercube": 78.70296236989591
        },
        "0.11988826320660662": {
            "0": 88.71096877502002,
            "1": 85.82866293034428,
            "2": 87.51000800640513,
            "3": 85.34827862289832,
            "hypercube": 73.3386709367494
        },
        "0.1591035847462855": {
            "0": 83.90712570056044,
            "1": 81.74539631705365,
            "2": 84.22738190552442,
            "3": 81.42514011208966,
            "hypercube": 65.65252201761409
        },
        "0.20472927123294937": {
            "0": 79.50360288230584,
            "1": 78.22257806244995,
            "2": 78.54283426741392,
            "3": 77.42193755004003,
            "hypercube": 55.80464371497198
        },
        "0.25991719550771475": {
            "0": 73.17854283426742,
            "1": 71.81745396317054,
            "2": 72.93835068054445,
            "3": 73.2586068855084,
            "hypercube": 49.31945556445156
        },
        "0.331259695023578": {
            "0": 68.05444355484389,
            "1": 66.37309847878302,
            "2": 66.45316253002403,
            "3": 67.09367493995197,
            "hypercube": 40.352281825460366
        },
        "0.4376586748096509": {
            "0": 57.886309047237795,
            "1": 55.80464371497198,
            "2": 56.925540432345876,
            "3": 56.04483586869495,
            "hypercube": 25.780624499599682
        }
    },
    "AVG": {
        "0.025996253574703254": {
            "0": 97.3109623698959,
            "1": 96.62268054443555,
            "2": 97.36697518014412,
            "3": 96.77471897518015,
            "hypercube": 94.79796317053643
        },
        "0.05425839099682417": {
            "0": 94.45380304243395,
            "1": 94.05364931945556,
            "2": 94.58977742193755,
            "3": 93.64546357085668,
            "hypercube": 89.05965732586068
        },
        "0.08530878077130555": {
            "0": 91.3165668534828,
            "1": 90.66032986389112,
            "2": 91.42061809447559,
            "3": 90.82040672538031,
            "hypercube": 81.56079423538831
        },
        "0.11988826320660662": {
            "0": 88.60372778222577,
            "1": 86.86690792634109,
            "2": 87.82720256204962,
            "3": 87.11504883907125,
            "hypercube": 74.65432185748598
        },
        "0.1591035847462855": {
            "0": 84.93008807045638,
            "1": 82.80951801441152,
            "2": 84.13768454763813,
            "3": 83.00138350680544,
            "hypercube": 66.33886309047237
        },
        "0.20472927123294937": {
            "0": 80.43217293835069,
            "1": 78.46379503602881,
            "2": 79.90399359487591,
            "3": 78.19959647718176,
            "hypercube": 56.88696877502002
        },
        "0.25991719550771475": {
            "0": 74.64607846277022,
            "1": 72.6614251401121,
            "2": 74.98994395516412,
            "3": 72.74967493995197,
            "hypercube": 48.73195836669335
        },
        "0.331259695023578": {
            "0": 67.87517694155326,
            "1": 66.00287590072057,
            "2": 68.36316413130503,
            "3": 65.82695916733385,
            "hypercube": 37.927532425940754
        },
        "0.4376586748096509": {
            "0": 57.886943154523614,
            "1": 55.95882145716573,
            "2": 57.55091753402722,
            "3": 55.35841152922338,
            "hypercube": 23.441453963170535
        }
    },
    "STD": {
        "0.025996253574703254": {
            "0": 0.6423717590138452,
            "1": 1.0626964920367843,
            "2": 0.5929159434019172,
            "3": 0.6433724119404857,
            "hypercube": 1.0303248425564262
        },
        "0.05425839099682417": {
            "0": 0.9160103376295847,
            "1": 1.0990786266996808,
            "2": 0.8686560894870601,
            "3": 1.3425122136781373,
            "hypercube": 2.200907582505893
        },
        "0.08530878077130555": {
            "0": 0.6957540156339286,
            "1": 1.0780865922791698,
            "2": 0.857721678817664,
            "3": 1.2616357361782737,
            "hypercube": 1.6026084550007351
        },
        "0.11988826320660662": {
            "0": 1.3419397240231736,
            "1": 1.4682280166840402,
            "2": 1.1711765992459864,
            "3": 1.5631148934131942,
            "hypercube": 2.8061573092198366
        },
        "0.1591035847462855": {
            "0": 1.1129527047039627,
            "1": 1.7930524987127994,
            "2": 1.2491056983028568,
            "3": 1.603164863100811,
            "hypercube": 1.9734417914810123
        },
        "0.20472927123294937": {
            "0": 1.5004020149950317,
            "1": 1.8593365407550466,
            "2": 1.3128858766059845,
            "3": 1.8512725434652877,
            "hypercube": 2.0133102037864212
        },
        "0.25991719550771475": {
            "0": 1.8842095914382997,
            "1": 1.8640905813879955,
            "2": 1.9506371069366686,
            "3": 2.2039035178974657,
            "hypercube": 3.0001480558482494
        },
        "0.331259695023578": {
            "0": 1.9060373589118575,
            "1": 1.9069557984362089,
            "2": 2.4144692692016854,
            "3": 2.147173597483858,
            "hypercube": 2.843800329400296
        },
        "0.4376586748096509": {
            "0": 1.2965075531052952,
            "1": 1.8637884417450559,
            "2": 1.903139513036153,
            "3": 2.1577715125953456,
            "hypercube": 2.3167596984006895
        }
    }
}