{
    "0": {
        "0.1": {
            "0": 87.36,
            "1": 88.96,
            "hypercube": 86.4
        },
        "0.2": {
            "0": 76.4,
            "1": 78.88,
            "hypercube": 75.76
        },
        "0.3": {
            "0": 69.84,
            "1": 69.52000000000001,
            "hypercube": 66.88
        },
        "0.4": {
            "0": 60.96,
            "1": 62.0,
            "hypercube": 56.39999999999999
        },
        "0.5": {
            "0": 55.04,
            "1": 55.92,
            "hypercube": 48.96
        },
        "0.6": {
            "0": 50.239999999999995,
            "1": 51.68000000000001,
            "hypercube": 44.0
        },
        "0.7": {
            "0": 44.24,
            "1": 43.2,
            "hypercube": 36.0
        },
        "0.8": {
            "0": 32.16,
            "1": 35.04,
            "hypercube": 25.679999999999996
        },
        "0.9": {
            "0": 18.08,
            "1": 24.08,
            "hypercube": 13.600000000000001
        }
    },
    "1": {
        "0.1": {
            "0": 94.32000000000001,
            "1": 91.52,
            "hypercube": 90.88000000000001
        },
        "0.2": {
            "0": 84.32,
            "1": 84.32,
            "hypercube": 81.76
        },
        "0.3": {
            "0": 76.48,
            "1": 76.72,
            "hypercube": 70.48
        },
        "0.4": {
            "0": 72.08,
            "1": 68.88,
            "hypercube": 62.88
        },
        "0.5": {
            "0": 60.64000000000001,
            "1": 58.56,
            "hypercube": 50.0
        },
        "0.6": {
            "0": 56.08,
            "1": 47.92,
            "hypercube": 39.519999999999996
        },
        "0.7": {
            "0": 45.92,
            "1": 39.6,
            "hypercube": 29.599999999999998
        },
        "0.8": {
            "0": 37.36,
            "1": 29.759999999999998,
            "hypercube": 17.84
        },
        "0.9": {
            "0": 18.72,
            "1": 18.32,
            "hypercube": 4.24
        }
    },
    "2": {
        "0.1": {
            "0": 85.52,
            "1": 86.32,
            "hypercube": 83.28
        },
        "0.2": {
            "0": 75.12,
            "1": 77.12,
            "hypercube": 71.52
        },
        "0.3": {
            "0": 69.28,
            "1": 71.36,
            "hypercube": 64.32
        },
        "0.4": {
            "0": 65.2,
            "1": 60.88,
            "hypercube": 52.080000000000005
        },
        "0.5": {
            "0": 56.32,
            "1": 53.52,
            "hypercube": 40.08
        },
        "0.6": {
            "0": 49.76,
            "1": 50.63999999999999,
            "hypercube": 36.32
        },
        "0.7": {
            "0": 32.48,
            "1": 42.88,
            "hypercube": 23.200000000000003
        },
        "0.8": {
            "0": 27.200000000000003,
            "1": 34.96,
            "hypercube": 16.16
        },
        "0.9": {
            "0": 16.32,
            "1": 20.96,
            "hypercube": 6.4799999999999995
        }
    },
    "3": {
        "0.1": {
            "0": 92.88,
            "1": 91.44,
            "hypercube": 91.03999999999999
        },
        "0.2": {
            "0": 83.84,
            "1": 87.76,
            "hypercube": 83.2
        },
        "0.3": {
            "0": 78.24,
            "1": 79.36,
            "hypercube": 72.32
        },
        "0.4": {
            "0": 70.24000000000001,
            "1": 70.72,
            "hypercube": 64.0
        },
        "0.5": {
            "0": 60.64000000000001,
            "1": 61.6,
            "hypercube": 52.959999999999994
        },
        "0.6": {
            "0": 55.04,
            "1": 51.28,
            "hypercube": 41.92
        },
        "0.7": {
            "0": 45.6,
            "1": 44.32,
            "hypercube": 35.199999999999996
        },
        "0.8": {
            "0": 30.4,
            "1": 32.879999999999995,
            "hypercube": 22.96
        },
        "0.9": {
            "0": 24.4,
            "1": 18.08,
            "hypercube": 12.32
        }
    },
    "4": {
        "0.1": {
            "0": 89.03999999999999,
            "1": 90.48,
            "hypercube": 87.03999999999999
        },
        "0.2": {
            "0": 83.91999999999999,
            "1": 85.36,
            "hypercube": 82.56
        },
        "0.3": {
            "0": 73.04,
            "1": 72.8,
            "hypercube": 69.36
        },
        "0.4": {
            "0": 65.03999999999999,
            "1": 67.12,
            "hypercube": 63.28
        },
        "0.5": {
            "0": 57.68,
            "1": 57.120000000000005,
            "hypercube": 51.76
        },
        "0.6": {
            "0": 45.92,
            "1": 45.36,
            "hypercube": 36.0
        },
        "0.7": {
            "0": 38.16,
            "1": 33.44,
            "hypercube": 23.119999999999997
        },
        "0.8": {
            "0": 28.96,
            "1": 22.16,
            "hypercube": 12.24
        },
        "0.9": {
            "0": 18.4,
            "1": 13.28,
            "hypercube": 4.08
        }
    },
    "5": {
        "0.1": {
            "0": 91.67333867093676,
            "1": 89.03122497998399,
            "hypercube": 88.31064851881504
        },
        "0.2": {
            "0": 83.58686949559647,
            "1": 81.66533226581265,
            "hypercube": 80.54443554843876
        },
        "0.3": {
            "0": 78.06244995996798,
            "1": 77.822257806245,
            "hypercube": 75.18014411529224
        },
        "0.4": {
            "0": 68.9351481184948,
            "1": 68.9351481184948,
            "hypercube": 66.37309847878302
        },
        "0.5": {
            "0": 59.48759007205765,
            "1": 57.245796637309844,
            "hypercube": 48.678943154523616
        },
        "0.6": {
            "0": 46.5972778222578,
            "1": 48.27862289831866,
            "hypercube": 32.66613290632506
        },
        "0.7": {
            "0": 41.23298638911129,
            "1": 39.31144915932746,
            "hypercube": 26.020816653322658
        },
        "0.8": {
            "0": 28.262610088070456,
            "1": 29.62369895916733,
            "hypercube": 15.692554043234589
        },
        "0.9": {
            "0": 18.494795836669336,
            "1": 16.493194555644518,
            "hypercube": 6.805444355484387
        }
    },
    "6": {
        "0.1": {
            "0": 92.87429943955165,
            "1": 93.59487590072058,
            "hypercube": 91.99359487590073
        },
        "0.2": {
            "0": 85.02802241793435,
            "1": 85.42834267413932,
            "hypercube": 84.30744595676542
        },
        "0.3": {
            "0": 77.822257806245,
            "1": 75.26020816653323,
            "hypercube": 74.05924739791834
        },
        "0.4": {
            "0": 62.93034427542034,
            "1": 66.61329063250601,
            "hypercube": 60.92874299439551
        },
        "0.5": {
            "0": 54.60368294635709,
            "1": 57.56605284227382,
            "hypercube": 50.120096076861486
        },
        "0.6": {
            "0": 41.79343474779824,
            "1": 48.678943154523616,
            "hypercube": 37.389911929543636
        },
        "0.7": {
            "0": 30.66453162530024,
            "1": 40.0320256204964,
            "hypercube": 26.421136909527622
        },
        "0.8": {
            "0": 23.218574859887912,
            "1": 28.742994395516412,
            "hypercube": 18.734987990392312
        },
        "0.9": {
            "0": 10.968775020016013,
            "1": 20.816653322658127,
            "hypercube": 7.44595676541233
        }
    },
    "7": {
        "0.1": {
            "0": 92.3138510808647,
            "1": 91.75340272217774,
            "hypercube": 90.79263410728583
        },
        "0.2": {
            "0": 86.6293034427542,
            "1": 84.86789431545236,
            "hypercube": 83.58686949559647
        },
        "0.3": {
            "0": 77.74219375500401,
            "1": 72.61809447558046,
            "hypercube": 70.37630104083267
        },
        "0.4": {
            "0": 72.05764611689351,
            "1": 63.81104883907126,
            "hypercube": 61.40912730184147
        },
        "0.5": {
            "0": 57.405924739791836,
            "1": 51.32105684547638,
            "hypercube": 46.677341873498804
        },
        "0.6": {
            "0": 49.47958366693355,
            "1": 43.074459567654124,
            "hypercube": 36.82946357085669
        },
        "0.7": {
            "0": 38.35068054443555,
            "1": 36.74939951961569,
            "hypercube": 27.141713370696557
        },
        "0.8": {
            "0": 21.056845476381106,
            "1": 24.579663730984787,
            "hypercube": 14.011208967173738
        },
        "0.9": {
            "0": 12.890312249799841,
            "1": 9.687750200160128,
            "hypercube": 5.204163330664532
        }
    },
    "8": {
        "0.1": {
            "0": 90.15212169735788,
            "1": 90.15212169735788,
            "hypercube": 88.951160928743
        },
        "0.2": {
            "0": 84.54763811048839,
            "1": 83.66693354683747,
            "hypercube": 81.66533226581265
        },
        "0.3": {
            "0": 75.5004003202562,
            "1": 76.46116893514812,
            "hypercube": 75.02001601281026
        },
        "0.4": {
            "0": 65.65252201761409,
            "1": 65.65252201761409,
            "hypercube": 61.569255404323464
        },
        "0.5": {
            "0": 59.00720576461169,
            "1": 57.726180944755804,
            "hypercube": 51.48118494795837
        },
        "0.6": {
            "0": 43.47477982385909,
            "1": 51.32105684547638,
            "hypercube": 38.67093674939952
        },
        "0.7": {
            "0": 36.188951160928745,
            "1": 43.074459567654124,
            "hypercube": 31.785428342674138
        },
        "0.8": {
            "0": 28.262610088070456,
            "1": 31.625300240192157,
            "hypercube": 20.656525220176142
        },
        "0.9": {
            "0": 16.33306645316253,
            "1": 17.373899119295437,
            "hypercube": 8.566853482786229
        }
    },
    "9": {
        "0.1": {
            "0": 88.55084067253803,
            "1": 88.07045636509207,
            "hypercube": 85.26821457165732
        },
        "0.2": {
            "0": 84.4675740592474,
            "1": 79.74379503602881,
            "hypercube": 78.62289831865492
        },
        "0.3": {
            "0": 71.97758206565253,
            "1": 71.97758206565253,
            "hypercube": 69.81585268214572
        },
        "0.4": {
            "0": 65.65252201761409,
            "1": 60.848678943154525,
            "hypercube": 58.366693354683754
        },
        "0.5": {
            "0": 54.84387510008006,
            "1": 54.68374699759808,
            "hypercube": 46.196957566052845
        },
        "0.6": {
            "0": 45.87670136108887,
            "1": 42.67413931144916,
            "hypercube": 32.2658126501201
        },
        "0.7": {
            "0": 38.8310648518815,
            "1": 33.38670936749399,
            "hypercube": 23.53883106485188
        },
        "0.8": {
            "0": 28.823058446757404,
            "1": 25.22017614091273,
            "hypercube": 15.932746196957567
        },
        "0.9": {
            "0": 16.172938350680543,
            "1": 18.8951160928743,
            "hypercube": 9.047237790232186
        }
    },
    "AVG": {
        "0.1": {
            "0": 90.4684451561249,
            "1": 90.13220816653322,
            "hypercube": 88.39562530024018
        },
        "0.2": {
            "0": 82.78594075260207,
            "1": 82.88122978382708,
            "hypercube": 80.35269815852682
        },
        "0.3": {
            "0": 74.79848839071258,
            "1": 74.38993114491593,
            "hypercube": 70.78115612489992
        },
        "0.4": {
            "0": 66.87481825460368,
            "1": 65.54606885508406,
            "hypercube": 60.72869175340272
        },
        "0.5": {
            "0": 57.566827862289834,
            "1": 56.526283426741394,
            "hypercube": 48.69145236188951
        },
        "0.6": {
            "0": 48.42617774219375,
            "1": 48.090722177742194,
            "hypercube": 37.558225780624504
        },
        "0.7": {
            "0": 39.16682145716573,
            "1": 39.599404323458764,
            "hypercube": 28.20279263410729
        },
        "0.8": {
            "0": 28.57036989591673,
            "1": 29.45918334667734,
            "hypercube": 17.990802241793435
        },
        "0.9": {
            "0": 17.077988791032826,
            "1": 17.79866132906325,
            "hypercube": 7.778965572457968
        }
    },
    "STD": {
        "0.1": {
            "0": 2.669508597560352,
            "1": 1.9936390983317158,
            "hypercube": 2.7192328467641356
        },
        "0.2": {
            "0": 3.614812276433448,
            "1": 3.2185745720460828,
            "hypercube": 3.806850590728997
        },
        "0.3": {
            "0": 3.3123451939042123,
            "1": 3.0222922772222574,
            "hypercube": 3.325727094259136
        },
        "0.4": {
            "0": 3.5948375392091214,
            "1": 3.3529187553242332,
            "hypercube": 3.9245907293571576
        },
        "0.5": {
            "0": 2.2096521444204593,
            "1": 2.7048903855301307,
            "hypercube": 3.5168301448133334
        },
        "0.6": {
            "0": 4.394742195378082,
            "1": 3.1993413163745106,
            "hypercube": 3.493867731251747
        },
        "0.7": {
            "0": 4.9463129467225935,
            "1": 3.7817334259057738,
            "hypercube": 4.541159310101678
        },
        "0.8": {
            "0": 4.252862051032883,
            "1": 4.165165078382777,
            "hypercube": 3.9150681556907045
        },
        "0.9": {
            "0": 3.4332904271129854,
            "1": 3.849682556400127,
            "hypercube": 3.0383695867008393
        }
    }
}